{
  "trailName": "Wirepatch",
  "trailSlug": "wirepatch",
  "resort": "breckenridge",
  "resortName": "Breckenridge",
  "area": "Peak 7",
  "difficulty": "Blue",
  "trailType": "Skiing",
  "currentStatus": {
    "date": "2025-11-19",
    "isOpen": false,
    "isGroomed": true,
    "groomingStatus": "Groomed",
    "status": "Closed"
  },
  "stats": {
    "seasonStartDate": "2025-10-25",
    "daysTracked": 5,
    "daysGroomed": 5,
    "groomingPercentage": 100,
    "currentStreak": 5,
    "longestStreak": 5,
    "lastGroomed": "2025-11-19",
    "dayOfWeek": [
      {
        "day": "Sun",
        "percentage": 100,
        "groomed": 1,
        "total": 1
      },
      {
        "day": "Mon",
        "percentage": 100,
        "groomed": 1,
        "total": 1
      },
      {
        "day": "Tue",
        "percentage": 100,
        "groomed": 1,
        "total": 1
      },
      {
        "day": "Wed",
        "percentage": 100,
        "groomed": 1,
        "total": 1
      },
      {
        "day": "Thu",
        "percentage": 0,
        "groomed": 0,
        "total": 0
      },
      {
        "day": "Fri",
        "percentage": 0,
        "groomed": 0,
        "total": 0
      },
      {
        "day": "Sat",
        "percentage": 100,
        "groomed": 1,
        "total": 1
      }
    ]
  },
  "history": [
    {
      "date": "2025-11-19",
      "isOpen": false,
      "isGroomed": true,
      "groomingStatus": "Groomed",
      "groomingType": "Skiing"
    },
    {
      "date": "2025-11-18",
      "isOpen": false,
      "isGroomed": true,
      "groomingStatus": "Groomed",
      "groomingType": "Skiing"
    },
    {
      "date": "2025-11-17",
      "isOpen": false,
      "isGroomed": true,
      "groomingStatus": "Groomed",
      "groomingType": "Skiing"
    },
    {
      "date": "2025-11-16",
      "isOpen": false,
      "isGroomed": true,
      "groomingStatus": "Groomed",
      "groomingType": "Skiing"
    },
    {
      "date": "2025-11-15",
      "isOpen": false,
      "isGroomed": true,
      "groomingStatus": "Groomed",
      "groomingType": "Skiing"
    }
  ],
  "generated": "2025-11-20T12:48:50.872Z"
}